j1939parser/__init__.py
j1939parser/core.py
j1939parser-0.1.4.dist-info/licenses/LICENSE
j1939parser-0.1.4.dist-info/METADATA
j1939parser-0.1.4.dist-info/WHEEL
j1939parser-0.1.4.dist-info/top_level.txt
j1939parser-0.1.4.dist-info/RECORD
